Workbook
Name unit_price: '入力'!$C$5
Name sales_total: '入力'!$C$6
Name n_all: '入力'!$C$7
Name n_resp: '入力'!$C$8
Name rx_resp: '入力'!$C$9
Name mkt_share: '入力'!$C$10
Name sales_per_pt: '入力'!$C$11
Name conv_low: '入力'!$C$12
Name conv_base: '入力'!$C$13
Name conv_high: '入力'!$C$14
Name prod_cost: '入力'!$C$15
Name ops_cost: '入力'!$C$16

Sheet 入力
A1: ① 入力(黄色=仮定・施策の設定、青=実測、灰=資料。色のセルを変えると全シートが再計算されます)
A2: 対象: 2026年アンケート回答医師5,000名。期間: 1年(MR君・MR面談は2025年6月〜2026年6月の活動。データ仕様書)
A4: 区分 | B4: 項目 | C4: 値 | D4: 単位 | E4: 名前 | F4: 出典・根拠
A5: 資料 | B5: 既読単価 | C5: 400 | D5: 円/既読 | E5: unit_price | F5: データ仕様書: MR君は既読1件あたり400円(配信ではなく既読で課金)
A6: 資料 | B6: 薬剤Aの年間売上 | C6: 5000000000 | D6: 円 | E6: sales_total | F6: 課題資料・データ仕様書
A7: 資料 | B7: 全医師数 | C7: 10000 | D7: 名 | E7: n_all | F7: データ仕様書: doctor_attributes「全10,000名」
A8: 資料 | B8: アンケート回答医師数 | C8: 5000 | D8: 名 | E8: n_resp | F8: survey_2026
A9: 実測 | B9: 回答医師の薬剤A処方患者数 | C9: 11280 | D9: 人 | E9: rx_resp | F9: survey_2026 Q3_2の合計(直近1年・自己申告)
A10: 仮定 | B10: 全医師10,000名の処方が売上50億円に占める割合 | C10: 1 | E10: mkt_share | F10: 仮定(要確認)。データ仕様書で10,000名が「全医師」のため100%
A11: 仮定 | B11: 処方患者1人あたり年間売上 | C11: =sales_total*mkt_share/(rx_resp*n_all/n_resp) | D11: 円 | E11: sales_per_pt | F11: 初期値=50億円×割合÷全医師の処方患者推計(回答医師×2)。実際の単価が分かれば数値で上書き
A12: 仮定 | B12: 増分転換率_保守 | C12: 0.01 | E12: conv_low | F12: 既読した医師の潜在未処方のうち、配信によって新たに処方される割合。配信を減らす群で失う効果にも同じ値を使う。⑦参照
A13: 仮定 | B13: 増分転換率_基準 | C13: 0.03 | E13: conv_base | F13: 参考値(配信対象と対象外の差から換算)の95%区間の下限2.8%に相当
A14: 仮定 | B14: 増分転換率_楽観 | C14: 0.06 | E14: conv_high | F14: 参考値の中央6.0%に相当(観察された差をすべて配信の効果とみなす)
A15: 未確認 | B15: コンテンツ制作費(年) | C15: 0 | D15: 円 | E15: prod_cost | F15: 既存10本の並べ替え・再配信のみの前提で0。新規制作する場合は入力
A16: 未確認 | B16: 配信設定・運用管理費(年) | C16: 0 | D16: 円 | E16: ops_cost | F16: 未確認。判明したら入力(A案・B案の費用に加算)
A18: 群別の入力(医師ごとに主要施策を1つ。群は重複しない)
A19: 群 | B19: 医師数 | C19: 潜在未処方(人) | D19: 1配信あたり既読率 | E19: 年10回配信時の既読医師率 | F19: 現状の年間配信回数 | G19: A案の年間配信回数 | H19: B案の年間配信回数 | I19: 翌年比(平均への回帰) | J19: 出典・根拠
A20: ① 未接触・潜在8人以上(重点医師) | B20: 191 | C20: 2042 | D20: 0.096938776 | E20: 0.4872449 | F20: 0 | G20: 12 | H20: 12 | I20: 0.77559055 | J20: 内科・耳鼻で潜在8人以上、MR面談なし・MR君未配信。既読率は配信中・MR面談なしの重点医師(②)の実測値を使う(仮定)
A21: ② 配信中・潜在8人以上(重点医師) | B21: 392 | C21: 4005 | D21: 0.096938776 | E21: 0.4872449 | F21: 10 | G21: 12 | H21: 12 | I21: 0.77559055 | J21: 内科・耳鼻で潜在8人以上、MR面談なし・MR君配信中。既読率は実測
A22: ③ 配信中・潜在0〜2人(財源) | B22: 993 | C22: 1511 | D22: 0.11732125 | E22: 0.51158107 | F22: 10 | G22: 6 | H22: 6 | I22: 2.1606061 | J22: A案の財源。全診療科で潜在0〜2人の配信対象。翌年比は全診療科・潜在0〜2人の実測値(平均への回帰で翌年は増える)
A23: ④ MR面談あり・潜在8人以上(重点医師、配信中) | B23: 82 | C23: 787 | D23: 0.091463415 | E23: 0.3902439 | F23: 10 | G23: 10 | H23: 10 | I23: 0.77559055 | J23: 重点医師のうちMR面談あり(118名)で配信中の82名。現状維持
A24: ⑤ 未接触・潜在5〜7人(B案で追加) | B24: 260 | C24: 1546 | D24: 0.11916168 | E24: 0.52295409 | F24: 0 | G24: 0 | H24: 12 | I24: 1.0179372 | J24: B案で追加。既読率は同じ条件(内科・耳鼻・面談なし・潜在5〜7人)で配信中の医師の実測値
A25: その他の配信中(変更なし) | B25: 2014 | C25: 9421 | D25: 0.1183714 | F25: 10 | G25: 10 | H25: 10 | I25: 1 | J25: 上記以外の配信対象。既読率は残りの既読件数から逆算

Sheet 医師セグメント
A1: ② 医師セグメント別施策表: 施策①(配信対象・回数)と施策②(診療科別の配信順)。重点医師 = 内科・耳鼻咽喉科で潜在未処方8人以上(701名)
A2: 群は潜在未処方と接触状況(MR面談・MR君)で分け、各医師は1つの群だけに属する。数値は回答医師ベース・A案の値(⑤はB案の値)。配信順は下の表(コンテンツ名と主要テーマで分類。本文は未確認)
A4: 医師セグメント | B4: 対象医師数 | C4: 潜在患者数 | D4: 発見された課題 | E4: 類似高処方医師との違い | F4: 推奨コンテンツ | G4: 配信回数(年) | H4: 想定既読件数(年) | I4: 想定費用(年、円) | J4: 期待する行動変化 | K4: KPI | L4: なぜこの医師に、この内容を、この回数送るのか
A5: ① 新規配信: MR面談もMR君もない重点医師 (内科89・耳鼻102) | B5: ='入力'!$B$20 | C5: ='入力'!$C$20 | D5: MR面談もMR君の配信もない。1人あたり潜在未処方10.7人と最も多い | E5: 類似高処方医師はMR面談あり51%(重点医師は17%)。理解度は5段階で2.1 vs 3.8 | F5: 診療科別の配信順(内科: C04→C03→C05→…/耳鼻: C05→C03→C01→…)。11・12回目は未読の1〜3本目を再配信 | G5: ='入力'!$G$20 | H5: ='④費用計算'!E6 | I5: ='④費用計算'!H6 | J5: MR君で薬剤Aの情報に初めて接し、重視する特性の理解を深める | K5: 既読医師率55%(想定)、最重視テーマの既読率、理解度(次回調査) | L5: 潜在患者が最も多いのに、MRもMR君も届いていない。既存の配信基盤に加えるだけで接点を作れる
A6: ② 増回: MR君のみの重点医師 (内科162・耳鼻230) | B6: ='入力'!$B$21 | C6: ='入力'!$C$21 | D6: 配信中でも約半数(51%)が1年間1本も読んでいない | E6: 重点医師の既読は配信対象1人あたり年0.96件(類似高処方医師1.31件)。MR面談あり17% vs 51% | F6: ①と同じ配信順。11・12回目は未読の1〜3本目を再配信 | G6: ='入力'!$G$21 | H6: ='④費用計算'!E7 | I6: ='④費用計算'!H7 | J6: 重視テーマを読み、理解度を上げる | K6: 既読医師率49%→55%(想定)、最重視テーマの既読率 | L6: MRが会えていない重点医師の主な接点はMR君。読まれていない重視テーマを再配信する(年10回→12回)
A7: ③ 隔月に: 潜在患者0〜2人の医師(全診療科) (内科343・耳鼻67・小児390・眼科193) | B7: ='入力'!$B$22 | C7: ='入力'!$C$22 | D7: 1人あたり潜在未処方1.5人。それでも配信率は71%で、潜在8人以上の医師(68%)と同じ水準 | E7: (重点医師ではない) | F7: 診療科別の配信順の上位6本(小児科・眼科はC03→C05→…) | G7: ='入力'!$G$22 | H7: ='④費用計算'!E8 | I7: ='④費用計算'!H8 | J7: 隔月でも重視テーマを受け取る | K7: 処方率の維持(次回調査)、配信停止の件数 | L7: 潜在患者数に合わせて配信を配分し直す。翌年に潜在が増える分(平均への回帰)を見込んでも、既読1件あたりの効果は①の約3割
A8: ④ 現状維持: MR面談がある重点医師(配信中82名) (内科31・耳鼻51) | B8: ='入力'!$B$23 | C8: ='入力'!$C$23 | D8: MR面談あり。最も参考にした情報源の97%がMR対面 | E8: MR面談がある(類似高処方医師もMR面談あり51%) | F8: 回数は変えず、配信順だけ診療科別にする | G8: ='入力'!$G$23 | H8: ='④費用計算'!E9 | I8: ='④費用計算'!H9 | J8: MR面談で情報を得る(MR君は補完) | K8: 現状維持 | L8: 主な情報源がMR対面のため、MR君の回数は増やさない。MR面談のない残り36名はMR対応のまま
A9: ⑤ B案で新規配信: 未接触・潜在5〜7人 (内科162・耳鼻98) | B9: ='入力'!$B$24 | C9: ='入力'!$C$24 | D9: MR面談もMR君の配信もない。1人あたり潜在未処方5.9人 | E9: 重点医師(潜在8人以上)の次に潜在が多い未接触の医師 | F9: ①と同じ配信順 | G9: ='入力'!$H$24 | H9: ='④費用計算'!F10 | I9: ='④費用計算'!I10 | J9: MR君で接点を持つ | K9: 既読医師率59%(想定)、理解度(次回調査) | L9: 追加予算がある場合に、未接触の中で次に潜在が多い医師へ月1回で広げる
A12: 施策② 診療科別の配信順(各特性の代表コンテンツ1本ずつを、その特性を最も重視する医師が多い順に。各特性の2本目以降は後半)
A13: 診療科 | B13: 重視の割合の基準 | C13: 1本目 | D13: 2本目 | E13: 3本目 | F13: 4本目 | G13: 5本目 | H13: 6本目 | I13: 7本目 | J13: 8本目 | K13: 9本目 | L13: 10本目
A14: 内科 | B14: 重点医師292名 | C14: C04 飲み合わせガイド (飲み合わせ: 最重視58%) | D14: C03 副作用プロファイル (副作用の少なさ: 最重視22%) | E14: C05 24時間カバーの臨床エビデンス (24h持続性: 最重視15%) | F14: C01 即効メカニズム (効果発現速度: 最重視5%) | G14: C02 幅広い適応症例集 (適用症状の広さ: 最重視0%) | H14: C09 多剤併用患者への処方設計 (飲み合わせ: 最重視58%) | I14: C10 長期投与の安全性と有効性 (24h持続性: 最重視15%) | J14: C07 即効性×持続性 (効果発現速度: 最重視5%) | K14: C06 2026年最新トレンド (効果発現速度: 最重視5%) | L14: C08 QOL改善効果 (適用症状の広さ: 最重視0%)
A15: 耳鼻咽喉科 | B15: 重点医師409名 | C15: C05 24時間カバーの臨床エビデンス (24h持続性: 最重視44%) | D15: C03 副作用プロファイル (副作用の少なさ: 最重視29%) | E15: C01 即効メカニズム (効果発現速度: 最重視16%) | F15: C04 飲み合わせガイド (飲み合わせ: 最重視11%) | G15: C02 幅広い適応症例集 (適用症状の広さ: 最重視0%) | H15: C10 長期投与の安全性と有効性 (24h持続性: 最重視44%) | I15: C07 即効性×持続性 (効果発現速度: 最重視16%) | J15: C06 2026年最新トレンド (効果発現速度: 最重視16%) | K15: C09 多剤併用患者への処方設計 (飲み合わせ: 最重視11%) | L15: C08 QOL改善効果 (適用症状の広さ: 最重視0%)
A16: 小児科 | B16: 全回答医師1,232名 | C16: C03 副作用プロファイル (副作用の少なさ: 最重視65%) | D16: C05 24時間カバーの臨床エビデンス (24h持続性: 最重視19%) | E16: C04 飲み合わせガイド (飲み合わせ: 最重視10%) | F16: C01 即効メカニズム (効果発現速度: 最重視7%) | G16: C02 幅広い適応症例集 (適用症状の広さ: 最重視0%) | H16: C10 長期投与の安全性と有効性 (24h持続性: 最重視19%) | I16: C09 多剤併用患者への処方設計 (飲み合わせ: 最重視10%) | J16: C07 即効性×持続性 (効果発現速度: 最重視7%) | K16: C06 2026年最新トレンド (効果発現速度: 最重視7%) | L16: C08 QOL改善効果 (適用症状の広さ: 最重視0%)
A17: 眼科 | B17: 全回答医師482名 | C17: C03 副作用プロファイル (副作用の少なさ: 最重視50%) | D17: C05 24時間カバーの臨床エビデンス (24h持続性: 最重視30%) | E17: C01 即効メカニズム (効果発現速度: 最重視12%) | F17: C04 飲み合わせガイド (飲み合わせ: 最重視9%) | G17: C02 幅広い適応症例集 (適用症状の広さ: 最重視0%) | H17: C10 長期投与の安全性と有効性 (24h持続性: 最重視30%) | I17: C07 即効性×持続性 (効果発現速度: 最重視12%) | J17: C06 2026年最新トレンド (効果発現速度: 最重視12%) | K17: C09 多剤併用患者への処方設計 (飲み合わせ: 最重視9%) | L17: C08 QOL改善効果 (適用症状の広さ: 最重視0%)
A19: 年12回の群(①②⑤)は10本を上の順で配信し、11・12回目に未読の1〜3本目を再配信。③(隔月)は上位6本。④は回数を変えず順番のみ。

Sheet ③配信計画
A1: ③ 配信計画(誰に・何回)
A4: 群 | B4: 現状回数 | C4: A案回数 | D4: B案回数 | E4: 配信医師数_現状 | F4: 配信医師数_A案 | G4: 配信医師数_B案 | H4: 配信件数_現状 | I4: 配信件数_A案 | J4: 配信件数_B案
A5: ① 未接触・潜在8人以上(重点医師) | B5: ='入力'!$F$20 | C5: ='入力'!$G$20 | D5: ='入力'!$H$20 | E5: =IF('入力'!$F$20>0,'入力'!$B$20,0) | F5: =IF('入力'!$G$20>0,'入力'!$B$20,0) | G5: =IF('入力'!$H$20>0,'入力'!$B$20,0) | H5: ='入力'!$B$20*'入力'!$F$20 | I5: ='入力'!$B$20*'入力'!$G$20 | J5: ='入力'!$B$20*'入力'!$H$20
A6: ② 配信中・潜在8人以上(重点医師) | B6: ='入力'!$F$21 | C6: ='入力'!$G$21 | D6: ='入力'!$H$21 | E6: =IF('入力'!$F$21>0,'入力'!$B$21,0) | F6: =IF('入力'!$G$21>0,'入力'!$B$21,0) | G6: =IF('入力'!$H$21>0,'入力'!$B$21,0) | H6: ='入力'!$B$21*'入力'!$F$21 | I6: ='入力'!$B$21*'入力'!$G$21 | J6: ='入力'!$B$21*'入力'!$H$21
A7: ③ 配信中・潜在0〜2人(財源) | B7: ='入力'!$F$22 | C7: ='入力'!$G$22 | D7: ='入力'!$H$22 | E7: =IF('入力'!$F$22>0,'入力'!$B$22,0) | F7: =IF('入力'!$G$22>0,'入力'!$B$22,0) | G7: =IF('入力'!$H$22>0,'入力'!$B$22,0) | H7: ='入力'!$B$22*'入力'!$F$22 | I7: ='入力'!$B$22*'入力'!$G$22 | J7: ='入力'!$B$22*'入力'!$H$22
A8: ④ MR面談あり・潜在8人以上(重点医師、配信中) | B8: ='入力'!$F$23 | C8: ='入力'!$G$23 | D8: ='入力'!$H$23 | E8: =IF('入力'!$F$23>0,'入力'!$B$23,0) | F8: =IF('入力'!$G$23>0,'入力'!$B$23,0) | G8: =IF('入力'!$H$23>0,'入力'!$B$23,0) | H8: ='入力'!$B$23*'入力'!$F$23 | I8: ='入力'!$B$23*'入力'!$G$23 | J8: ='入力'!$B$23*'入力'!$H$23
A9: ⑤ 未接触・潜在5〜7人(B案で追加) | B9: ='入力'!$F$24 | C9: ='入力'!$G$24 | D9: ='入力'!$H$24 | E9: =IF('入力'!$F$24>0,'入力'!$B$24,0) | F9: =IF('入力'!$G$24>0,'入力'!$B$24,0) | G9: =IF('入力'!$H$24>0,'入力'!$B$24,0) | H9: ='入力'!$B$24*'入力'!$F$24 | I9: ='入力'!$B$24*'入力'!$G$24 | J9: ='入力'!$B$24*'入力'!$H$24
A10: その他の配信中(変更なし) | B10: ='入力'!$F$25 | C10: ='入力'!$G$25 | D10: ='入力'!$H$25 | E10: =IF('入力'!$F$25>0,'入力'!$B$25,0) | F10: =IF('入力'!$G$25>0,'入力'!$B$25,0) | G10: =IF('入力'!$H$25>0,'入力'!$B$25,0) | H10: ='入力'!$B$25*'入力'!$F$25 | I10: ='入力'!$B$25*'入力'!$G$25 | J10: ='入力'!$B$25*'入力'!$H$25
A11: 合計 | E11: =SUM(E5:E10) | F11: =SUM(F5:F10) | G11: =SUM(G5:G10) | H11: =SUM(H5:H10) | I11: =SUM(I5:I10) | J11: =SUM(J5:J10)

Sheet ④費用計算
A1: ④ 費用計算: 既読件数 = 医師数 × 年間配信回数 × 1配信あたり既読率 / 費用 = 既読件数 × 既読単価
A2: 現状費用は回答医師分(全医師10,000名では既読8,192件・327.7万円)。配信設定・運用・制作費は未確認(①で入力)
A5: 群 | B5: 既読件数_現状 | C5: 費用_現状 | E5: 既読件数_A案 | F5: 既読件数_B案 | H5: 費用_A案 | I5: 費用_B案
A6: ① 未接触・潜在8人以上(重点医師) | B6: ='入力'!$B$20*'入力'!$F$20*'入力'!$D$20 | C6: =B6*unit_price | E6: ='入力'!$B$20*'入力'!$G$20*'入力'!$D$20 | F6: ='入力'!$B$20*'入力'!$H$20*'入力'!$D$20 | H6: =E6*unit_price | I6: =F6*unit_price
A7: ② 配信中・潜在8人以上(重点医師) | B7: ='入力'!$B$21*'入力'!$F$21*'入力'!$D$21 | C7: =B7*unit_price | E7: ='入力'!$B$21*'入力'!$G$21*'入力'!$D$21 | F7: ='入力'!$B$21*'入力'!$H$21*'入力'!$D$21 | H7: =E7*unit_price | I7: =F7*unit_price
A8: ③ 配信中・潜在0〜2人(財源) | B8: ='入力'!$B$22*'入力'!$F$22*'入力'!$D$22 | C8: =B8*unit_price | E8: ='入力'!$B$22*'入力'!$G$22*'入力'!$D$22 | F8: ='入力'!$B$22*'入力'!$H$22*'入力'!$D$22 | H8: =E8*unit_price | I8: =F8*unit_price
A9: ④ MR面談あり・潜在8人以上(重点医師、配信中) | B9: ='入力'!$B$23*'入力'!$F$23*'入力'!$D$23 | C9: =B9*unit_price | E9: ='入力'!$B$23*'入力'!$G$23*'入力'!$D$23 | F9: ='入力'!$B$23*'入力'!$H$23*'入力'!$D$23 | H9: =E9*unit_price | I9: =F9*unit_price
A10: ⑤ 未接触・潜在5〜7人(B案で追加) | B10: ='入力'!$B$24*'入力'!$F$24*'入力'!$D$24 | C10: =B10*unit_price | E10: ='入力'!$B$24*'入力'!$G$24*'入力'!$D$24 | F10: ='入力'!$B$24*'入力'!$H$24*'入力'!$D$24 | H10: =E10*unit_price | I10: =F10*unit_price
A11: その他の配信中(変更なし) | B11: ='入力'!$B$25*'入力'!$F$25*'入力'!$D$25 | C11: =B11*unit_price | E11: ='入力'!$B$25*'入力'!$G$25*'入力'!$D$25 | F11: ='入力'!$B$25*'入力'!$H$25*'入力'!$D$25 | H11: =E11*unit_price | I11: =F11*unit_price
A12: 既読費用 合計 | B12: =SUM(B6:B11) | C12: =SUM(C6:C11) | E12: =SUM(E6:E11) | F12: =SUM(F6:F11) | H12: =SUM(H6:H11) | I12: =SUM(I6:I11)
A13: 制作費・運用費(未確認) | C13: 0 | H13: =prod_cost+ops_cost | I13: =prod_cost+ops_cost
A14: 総費用 | C14: =C12+C13 | H14: =H12+H13 | I14: =I12+I13
A15: 現状からの追加費用 | H15: =H14-C14 | I15: =I14-C14
A16: 予算判定(A案は現状費用以内か) | H16: =IF(H14<=C14,"予算内","予算超過")

Sheet ⑤売上試算
A1: ⑤ 売上試算: 既読医師率(f回) = 1 −(1 − 10回時の既読医師率)^(f/10) / 追加処方患者 = 既読医師の増減 × 1人あたり潜在未処方 × 翌年比 × 増分転換率
A2: 翌年比 = 平均への回帰の補正(潜在の多い医師は翌年に潜在が減り、少ない医師は増える)。配信を減らす③は、失う効果を同じ転換率で差し引く。施策②(配信順)の上乗せは含めない。現状との差のみ。各医師は1つの群だけに属するため二重計上はない。売上であり利益ではない
H3: 追加処方患者(人)
A4: 群 | B4: 1人あたり潜在未処方 | C4: 既読医師率_現状 | D4: 既読医師率_A案 | E4: 既読医師率_B案 | F4: 既読医師の増減_A案 | G4: 既読医師の増減_B案 | H4: A案_保守 | I4: A案_基準 | J4: A案_楽観 | K4: B案_保守 | L4: B案_基準 | M4: B案_楽観
A5: ① 未接触・潜在8人以上(重点医師) | B5: ='入力'!$C$20/'入力'!$B$20 | C5: =IF(OR('入力'!$E$20="",'入力'!$F$20=0),0,1-(1-'入力'!$E$20)^('入力'!$F$20/10)) | D5: =IF(OR('入力'!$E$20="",'入力'!$G$20=0),0,1-(1-'入力'!$E$20)^('入力'!$G$20/10)) | E5: =IF(OR('入力'!$E$20="",'入力'!$H$20=0),0,1-(1-'入力'!$E$20)^('入力'!$H$20/10)) | F5: =IF('入力'!$E$20="",0,'入力'!$B$20*(D5-C5)) | G5: =IF('入力'!$E$20="",0,'入力'!$B$20*(E5-C5)) | H5: =F5*B5*'入力'!$I$20*conv_low | I5: =F5*B5*'入力'!$I$20*conv_base | J5: =F5*B5*'入力'!$I$20*conv_high | K5: =G5*B5*'入力'!$I$20*conv_low | L5: =G5*B5*'入力'!$I$20*conv_base | M5: =G5*B5*'入力'!$I$20*conv_high
A6: ② 配信中・潜在8人以上(重点医師) | B6: ='入力'!$C$21/'入力'!$B$21 | C6: =IF(OR('入力'!$E$21="",'入力'!$F$21=0),0,1-(1-'入力'!$E$21)^('入力'!$F$21/10)) | D6: =IF(OR('入力'!$E$21="",'入力'!$G$21=0),0,1-(1-'入力'!$E$21)^('入力'!$G$21/10)) | E6: =IF(OR('入力'!$E$21="",'入力'!$H$21=0),0,1-(1-'入力'!$E$21)^('入力'!$H$21/10)) | F6: =IF('入力'!$E$21="",0,'入力'!$B$21*(D6-C6)) | G6: =IF('入力'!$E$21="",0,'入力'!$B$21*(E6-C6)) | H6: =F6*B6*'入力'!$I$21*conv_low | I6: =F6*B6*'入力'!$I$21*conv_base | J6: =F6*B6*'入力'!$I$21*conv_high | K6: =G6*B6*'入力'!$I$21*conv_low | L6: =G6*B6*'入力'!$I$21*conv_base | M6: =G6*B6*'入力'!$I$21*conv_high
A7: ③ 配信中・潜在0〜2人(財源) | B7: ='入力'!$C$22/'入力'!$B$22 | C7: =IF(OR('入力'!$E$22="",'入力'!$F$22=0),0,1-(1-'入力'!$E$22)^('入力'!$F$22/10)) | D7: =IF(OR('入力'!$E$22="",'入力'!$G$22=0),0,1-(1-'入力'!$E$22)^('入力'!$G$22/10)) | E7: =IF(OR('入力'!$E$22="",'入力'!$H$22=0),0,1-(1-'入力'!$E$22)^('入力'!$H$22/10)) | F7: =IF('入力'!$E$22="",0,'入力'!$B$22*(D7-C7)) | G7: =IF('入力'!$E$22="",0,'入力'!$B$22*(E7-C7)) | H7: =F7*B7*'入力'!$I$22*conv_low | I7: =F7*B7*'入力'!$I$22*conv_base | J7: =F7*B7*'入力'!$I$22*conv_high | K7: =G7*B7*'入力'!$I$22*conv_low | L7: =G7*B7*'入力'!$I$22*conv_base | M7: =G7*B7*'入力'!$I$22*conv_high
A8: ④ MR面談あり・潜在8人以上(重点医師、配信中) | B8: ='入力'!$C$23/'入力'!$B$23 | C8: =IF(OR('入力'!$E$23="",'入力'!$F$23=0),0,1-(1-'入力'!$E$23)^('入力'!$F$23/10)) | D8: =IF(OR('入力'!$E$23="",'入力'!$G$23=0),0,1-(1-'入力'!$E$23)^('入力'!$G$23/10)) | E8: =IF(OR('入力'!$E$23="",'入力'!$H$23=0),0,1-(1-'入力'!$E$23)^('入力'!$H$23/10)) | F8: =IF('入力'!$E$23="",0,'入力'!$B$23*(D8-C8)) | G8: =IF('入力'!$E$23="",0,'入力'!$B$23*(E8-C8)) | H8: =F8*B8*'入力'!$I$23*conv_low | I8: =F8*B8*'入力'!$I$23*conv_base | J8: =F8*B8*'入力'!$I$23*conv_high | K8: =G8*B8*'入力'!$I$23*conv_low | L8: =G8*B8*'入力'!$I$23*conv_base | M8: =G8*B8*'入力'!$I$23*conv_high
A9: ⑤ 未接触・潜在5〜7人(B案で追加) | B9: ='入力'!$C$24/'入力'!$B$24 | C9: =IF(OR('入力'!$E$24="",'入力'!$F$24=0),0,1-(1-'入力'!$E$24)^('入力'!$F$24/10)) | D9: =IF(OR('入力'!$E$24="",'入力'!$G$24=0),0,1-(1-'入力'!$E$24)^('入力'!$G$24/10)) | E9: =IF(OR('入力'!$E$24="",'入力'!$H$24=0),0,1-(1-'入力'!$E$24)^('入力'!$H$24/10)) | F9: =IF('入力'!$E$24="",0,'入力'!$B$24*(D9-C9)) | G9: =IF('入力'!$E$24="",0,'入力'!$B$24*(E9-C9)) | H9: =F9*B9*'入力'!$I$24*conv_low | I9: =F9*B9*'入力'!$I$24*conv_base | J9: =F9*B9*'入力'!$I$24*conv_high | K9: =G9*B9*'入力'!$I$24*conv_low | L9: =G9*B9*'入力'!$I$24*conv_base | M9: =G9*B9*'入力'!$I$24*conv_high
A10: その他の配信中(変更なし) | B10: ='入力'!$C$25/'入力'!$B$25 | C10: =IF(OR('入力'!$E$25="",'入力'!$F$25=0),0,1-(1-'入力'!$E$25)^('入力'!$F$25/10)) | D10: =IF(OR('入力'!$E$25="",'入力'!$G$25=0),0,1-(1-'入力'!$E$25)^('入力'!$G$25/10)) | E10: =IF(OR('入力'!$E$25="",'入力'!$H$25=0),0,1-(1-'入力'!$E$25)^('入力'!$H$25/10)) | F10: =IF('入力'!$E$25="",0,'入力'!$B$25*(D10-C10)) | G10: =IF('入力'!$E$25="",0,'入力'!$B$25*(E10-C10)) | H10: =F10*B10*'入力'!$I$25*conv_low | I10: =F10*B10*'入力'!$I$25*conv_base | J10: =F10*B10*'入力'!$I$25*conv_high | K10: =G10*B10*'入力'!$I$25*conv_low | L10: =G10*B10*'入力'!$I$25*conv_base | M10: =G10*B10*'入力'!$I$25*conv_high
A11: 追加処方患者 合計 | F11: =SUM(F5:F10) | G11: =SUM(G5:G10) | H11: =SUM(H5:H10) | I11: =SUM(I5:I10) | J11: =SUM(J5:J10) | K11: =SUM(K5:K10) | L11: =SUM(L5:L10) | M11: =SUM(M5:M10)
A12: 追加売上(円) = 追加処方患者 × 処方患者1人あたり年間売上 | H12: =H11*sales_per_pt | I12: =I11*sales_per_pt | J12: =J11*sales_per_pt | K12: =K11*sales_per_pt | L12: =L11*sales_per_pt | M12: =M11*sales_per_pt

Sheet ⑥シナリオ比較
A1: ⑥ シナリオ比較: A案(予算維持型)とB案(追加投資型)
A2: A案: ①未接触の重点医師191名に新規配信(年12回)、②配信中の重点医師392名を年10回→12回、③潜在0〜2人の993名を年10回→6回(財源)。B案: A案+⑤未接触・潜在5〜7人の260名に新規配信(年12回)
A4: 項目 | B4: 現状 | C4: A案 予算維持型 | D4: B案 追加投資型 | E4: B案 − A案
A5: 配信対象医師数(名) | B5: ='③配信計画'!E11 | C5: ='③配信計画'!F11 | D5: ='③配信計画'!G11 | E5: =D5-C5
A6: 配信件数(件) | B6: ='③配信計画'!H11 | C6: ='③配信計画'!I11 | D6: ='③配信計画'!J11 | E6: =D6-C6
A7: 想定既読件数(件) | B7: ='④費用計算'!B12 | C7: ='④費用計算'!E12 | D7: ='④費用計算'!F12 | E7: =D7-C7
A8: 費用(円) | B8: ='④費用計算'!C14 | C8: ='④費用計算'!H14 | D8: ='④費用計算'!I14 | E8: =D8-C8
A9: 現状からの追加費用(円) | B9: 0 | C9: =C8-$B$8 | D9: =D8-$B$8 | E9: =D9-C9
A10: 潜在患者カバー数(人) | B10: =SUMPRODUCT(('入力'!$F$20:$F$25>0)*'入力'!$C$20:$C$25) | C10: =SUMPRODUCT(('入力'!$G$20:$G$25>0)*'入力'!$C$20:$C$25) | D10: =SUMPRODUCT(('入力'!$H$20:$H$25>0)*'入力'!$C$20:$C$25) | E10: =D10-C10
A11: 追加処方患者_保守(人) | B11: 0 | C11: ='⑤売上試算'!H11 | D11: ='⑤売上試算'!K11 | E11: =D11-C11
A12: 追加処方患者_基準(人) | B12: 0 | C12: ='⑤売上試算'!I11 | D12: ='⑤売上試算'!L11 | E12: =D12-C12
A13: 追加処方患者_楽観(人) | B13: 0 | C13: ='⑤売上試算'!J11 | D13: ='⑤売上試算'!M11 | E13: =D13-C13
A14: 追加売上_保守(円) | B14: 0 | C14: ='⑤売上試算'!H12 | D14: ='⑤売上試算'!K12 | E14: =D14-C14
A15: 追加売上_基準(円) | B15: 0 | C15: ='⑤売上試算'!I12 | D15: ='⑤売上試算'!L12 | E15: =D15-C15
A16: 追加売上_楽観(円) | B16: 0 | C16: ='⑤売上試算'!J12 | D16: ='⑤売上試算'!M12 | E16: =D16-C16
A17: 費用対効果(追加売上_基準 ÷ 追加費用) | C17: =IF(C9<=0,"追加費用なし",C15/C9) | D17: =IF(D9<=0,"追加費用なし",D15/D9) | E17: =IF(E9<=0,"",E15/E9)
A18: 費用回収に必要な利益率_保守(追加費用÷追加売上) | C18: =IF(C9<=0,"不要",C9/C14) | D18: =IF(D9<=0,"不要",D9/D14) | E18: =IF(E9<=0,"",E9/E14)
A19: 費用回収に必要な利益率_基準 | C19: =IF(C9<=0,"不要",C9/C15) | D19: =IF(D9<=0,"不要",D9/D15) | E19: =IF(E9<=0,"",E9/E15)
A20: 予算判定(A案) | C20: =IF(C8<=B8,"予算内","予算超過")
A22: 表示用(PPTと同じ丸め) | B22: 現状 | C22: A案 | D22: B案 | E22: B案 − A案
A23: 費用(万円、小数1桁) | B23: =ROUND(B8/10000,1) | C23: =ROUND(C8/10000,1) | D23: =ROUND(D8/10000,1) | E23: =ROUND(D8/10000,1)-ROUND(C8/10000,1)
A24: 追加費用(万円、小数1桁) | B24: =ROUND(B9/10000,1) | C24: =ROUND(C9/10000,1) | D24: =ROUND(D9/10000,1) | E24: =ROUND(D9/10000,1)-ROUND(C9/10000,1)
A25: 既読件数 | B25: =ROUND(B7,0) | C25: =ROUND(C7,0) | D25: =ROUND(D7,0) | E25: =ROUND(D7,0)-ROUND(C7,0)
A26: 追加処方患者_保守 | B26: =ROUND(B11,0) | C26: =ROUND(C11,0) | D26: =ROUND(D11,0) | E26: =ROUND(E11,0)
A27: 追加処方患者_基準 | B27: =ROUND(B12,0) | C27: =ROUND(C12,0) | D27: =ROUND(D12,0) | E27: =ROUND(E12,0)
A28: 追加処方患者_楽観 | B28: =ROUND(B13,0) | C28: =ROUND(C13,0) | D28: =ROUND(D13,0) | E28: =ROUND(E13,0)
A29: 追加売上_保守(万円) | B29: =ROUND(B14/10000,0) | C29: =ROUND(C14/10000,0) | D29: =ROUND(D14/10000,0) | E29: =ROUND(D14/10000,0)-ROUND(C14/10000,0)
A30: 追加売上_基準(万円) | B30: =ROUND(B15/10000,0) | C30: =ROUND(C15/10000,0) | D30: =ROUND(D15/10000,0) | E30: =ROUND(D15/10000,0)-ROUND(C15/10000,0)
A31: 追加売上_楽観(万円) | B31: =ROUND(B16/10000,0) | C31: =ROUND(C16/10000,0) | D31: =ROUND(D16/10000,0) | E31: =ROUND(D16/10000,0)-ROUND(C16/10000,0)

Sheet ⑦計算根拠・注意事項
A1: ⑦ 計算根拠・注意事項
A3: 【実測】医師数・潜在未処方・既読件数・既読医師率・翌年比は、2026年・2025年アンケート(回答5,000名)とMR君の配信対象・既読ログ(1年分)から集計(analysis/v5_analysis.py)。
A4: 【資料】既読単価400円、年間売上50億円、現状の配信は配信対象1名に10本(課題資料)。MR面談・MR君は2025年6月〜2026年6月の活動(データ仕様書)。
A5: 【施策①】潜在未処方と接触状況で配信対象・回数を決める。①未接触の重点医師に新規配信、②配信中の重点医師を年12回、③潜在0〜2人を隔月(財源)。④MR面談がある重点医師は現状維持。
A6: 【施策②】診療科ごとに、各特性の代表コンテンツ1本ずつを、その特性を最も重視する医師が多い順に配信(②シートの下の表)。コンテンツはコンテンツ名と主要テーマで分類し、本文は未確認(配信前に確認が必要)。
A7: 参考(実測): 配信対象の全回答医師3,481名で、本人が最も重視するテーマのコンテンツの既読率は13.9%、その他は11.0%。施策②の上乗せ効果は試算に含めない。
A8: 【仮定】処方患者1人あたり年間売上 = 50億円 ÷ 全医師の処方患者推計22,560人(回答医師11,280人×10,000/5,000)。全医師10,000名の処方が売上のすべてと仮定。実際の単価が分かれば①で上書き。
A9: 【仮定】既読医師率のモデル: 年f回配信時 = 1 −(1 − 10回時の既読医師率)^(f/10)。配信ごとの読まれやすさが一定と仮定。10回を超える分は未読の上位コンテンツの再配信。
A10: 【仮定】①未接触の重点医師の既読率は、配信中・MR面談なしの重点医師(②)の実測値を使う。
A11: 【補正】平均への回帰: MR面談・MR君の接点がない両年回答医師で、潜在8人以上だった医師の翌年の潜在は0.78倍、5〜7人は1.02倍、0〜2人は2.16倍(全診療科、M1)。翌年の潜在で効果を計算。
A12: 【仮定】増分転換率(保守1%・基準3%・楽観6%): 既読した医師の潜在未処方のうち、配信によって新たに処方される割合。配信を減らす③で失う効果も同じ値で差し引く。
A13: 参考値(観察、因果ではない): MR面談のない両年回答2,945名で、配信対象は対象外より処方率の伸びが2.3pt大きかった(95%区間1.1〜3.5pt)。既読医師1人・潜在あたりに換算すると約6.0%(下限2.8%)。楽観=中央、基準=下限、保守=約3分の1。
... A19: 【使わない分析】完読・コンテンツ別の処方効果・動画の長さの分析、医師の重視割合とコンテンツ本数の割合の比較、v3・v4の試算値は使用していない。
