Workbook
Name unit_price: '入力'!$C$5
Name sales_total: '入力'!$C$6
Name n_all: '入力'!$C$7
Name n_resp: '入力'!$C$8
Name rx_resp: '入力'!$C$9
Name mkt_share: '入力'!$C$10
Name sales_per_pt: '入力'!$C$11
Name conv_low: '入力'!$C$12
Name conv_base: '入力'!$C$13
Name conv_high: '入力'!$C$14
Name prod_cost: '入力'!$C$15
Name ops_cost: '入力'!$C$16

Sheet 入力
A1: ① 入力(黄色=仮定・施策の設定、青=実測、灰=資料。色のセルを変えると全シートが再計算されます)
A2: 対象: 2026年アンケート回答医師5,000名。期間: 1年(MR君・MR面談は2025年6月〜2026年6月の活動。データ仕様書)
A4: 区分 | B4: 項目 | C4: 値 | D4: 単位 | E4: 名前 | F4: 出典・根拠
A5: 資料 | B5: 既読単価 | C5: 400 | D5: 円/既読 | E5: unit_price | F5: データ仕様書: MR君は既読1件あたり400円(配信ではなく既読で課金)
A6: 資料 | B6: 薬剤Aの年間売上 | C6: 5000000000 | D6: 円 | E6: sales_total | F6: 課題資料・データ仕様書
A7: 資料 | B7: 全医師数 | C7: 10000 | D7: 名 | E7: n_all | F7: データ仕様書: doctor_attributes「全10,000名」
A8: 資料 | B8: アンケート回答医師数 | C8: 5000 | D8: 名 | E8: n_resp | F8: survey_2026
A9: 実測 | B9: 回答医師の薬剤A処方患者数 | C9: 11280 | D9: 人 | E9: rx_resp | F9: survey_2026 Q3_2の合計(直近1年・自己申告)
A10: 仮定 | B10: 全医師10,000名の処方が売上50億円に占める割合 | C10: 1 | E10: mkt_share | F10: 仮定(要確認)。データ仕様書で10,000名が「全医師」のため100%
A11: 仮定 | B11: 処方患者1人あたり年間売上 | C11: =sales_total*mkt_share/(rx_resp*n_all/n_resp) | D11: 円 | E11: sales_per_pt | F11: 初期値=50億円×割合÷全医師の処方患者推計(回答医師×2)。実際の単価が分かれば数値で上書き
A12: 仮定 | B12: 増分転換率_保守 | C12: 0.01 | E12: conv_low | F12: 既読した医師の潜在未処方のうち、配信によって新たに処方される割合。⑦参照
A13: 仮定 | B13: 増分転換率_基準 | C13: 0.03 | E13: conv_base | F13: 参考値(配信対象と対象外の差から換算)の95%区間の下限2.8%に相当
A14: 仮定 | B14: 増分転換率_楽観 | C14: 0.06 | E14: conv_high | F14: 参考値の中央6.0%に相当(観察された差をすべて配信の効果とみなす)
A15: 未確認 | B15: コンテンツ制作費(年) | C15: 0 | D15: 円 | E15: prod_cost | F15: 既存10本の並べ替え・再配信のみの前提で0。新規制作する場合は入力
A16: 未確認 | B16: 配信設定・運用管理費(年) | C16: 0 | D16: 円 | E16: ops_cost | F16: 未確認。判明したら入力(A案・B案の費用に加算)
A18: 群別の入力(医師ごとに主要施策を1つ。群は重複しない)
A19: 群 | B19: 医師数 | C19: 潜在未処方(人) | D19: 1配信あたり既読率 | E19: 年10回配信時の既読医師率 | F19: 現状の年間配信回数 | G19: A案の年間配信回数 | H19: B案の年間配信回数 | I19: 出典・根拠
A20: 接触不足型 | B20: 191 | C20: 2042 | D20: 0.093968254 | E20: 0.47301587 | F20: 0 | G20: 12 | H20: 12 | I20: 重点医師のうちMR面談なし・MR君未配信。既読率は似た状態で配信中の理解不足型の実測値
A21: 理解不足型 | B21: 315 | C21: 3274 | D21: 0.093968254 | E21: 0.47301587 | F21: 10 | G21: 12 | H21: 12 | I21: 重点医師のうちMR君配信中・面談なし・処方意向3以下。既読率は実測(既読296件÷315名×10回)
A22: 意向ギャップ型 | B22: 77 | C22: 731 | D22: 0.10909091 | E22: 0.54545455 | F22: 10 | G22: 24 | H22: 24 | I22: 重点医師のうちMR君配信中・面談なし・処方意向4以上。既読率は実測
A23: MR面談フォロー型(配信中) | B23: 82 | C23: 787 | D23: 0.091463415 | E23: 0.3902439 | F23: 10 | G23: 10 | H23: 10 | I23: 重点医師のうちMR面談あり(118名)で配信中の82名。現状維持
A24: 未接触×潜在5〜7人 | B24: 260 | C24: 1546 | D24: 0.11916168 | E24: 0.52295409 | F24: 0 | G24: 0 | H24: 12 | I24: B案で追加。既読率は同じ条件(内科・耳鼻・面談なし・潜在5〜7人)で配信中の医師の実測値
A25: 低優先(配信中×潜在0〜2人) | B25: 993 | C25: 1511 | D25: 0.11732125 | E25: 0.51158107 | F25: 10 | G25: 6 | H25: 6 | I25: A案の財源。全診療科の配信対象で潜在未処方0〜2人(1人あたり1.5人)
A26: その他の配信中(変更なし) | B26: 2014 | C26: 9421 | D26: 0.1183714 | F26: 10 | G26: 10 | H26: 10 | I26: 上記以外の配信対象。既読率は残りの既読件数から逆算

Sheet 医師セグメント
A1: ② 医師セグメント別施策表(重点医師701名 = 内科・耳鼻咽喉科で潜在未処方8人以上)
A2: 判定順: ①MR面談あり→MR面談フォロー型 ②MR君未配信→接触不足型 ③処方意向4以上→意向ギャップ型 ④それ以外→理解不足型。数値は回答医師ベース・A案(B案で追加する群はB案の値)。④は118名のうち配信中82名の値
A4: 医師セグメント | B4: 対象医師数 | C4: 潜在患者数 | D4: 発見された課題 | E4: 類似高処方医師との違い | F4: 推奨コンテンツ | G4: 配信回数(年) | H4: 想定既読件数(年) | I4: 想定費用(年、円) | J4: 期待する行動変化 | K4: KPI | L4: なぜこの医師に、この内容を、この回数送るのか
A5: ① 接触不足型 (内科89・耳鼻102) | B5: ='入力'!$B$20 | C5: ='入力'!$C$20 | D5: MR面談もMR君配信もない。理解度1.8・処方意向2.2・処方率13%。1人あたり潜在未処方10.7人(4タイプで最多) | E5: 類似高処方医師はMR面談あり51%・理解度3.8・意向4.6。重点医師は学会・論文を参考にする割合が2倍(24% vs 12%) | F5: 内科: ①C04 飲み合わせガイド ②C09 多剤併用患者への処方設計 ③C03 副作用 ④C05 24時間カバー → 残り6本 耳鼻: ①C05 24時間カバーの臨床エビデンス ②C10 長期投与の安全性と有効性 ③C03 副作用 ④C01 即効メカニズム → 残り6本 | G5: ='入力'!$G$20 | H5: ='④費用計算'!E6 | I5: ='④費用計算'!H6 | J5: MR君で初めて接点を持ち、重視テーマの理解を深める | K5: 既読医師率54%(想定)、次回調査の理解度・処方意向 | L5: 潜在が最も多いのに接点がない。学会・論文を参考にする医師が多いため、エビデンス型の重視テーマから始め、5特性すべてを月1回(10本+重視テーマの再配信2回)で届ける。
A6: ② 理解不足型 (内科150・耳鼻165) | B6: ='入力'!$B$21 | C6: ='入力'!$C$21 | D6: 配信中でも既読は年0.94件、53%が1年間未読。理解度1.8・処方意向2.1・処方率14% | E6: 理解度は5特性すべてで類似高処方医師より約2低い(1.8 vs 3.8)。重点医師は配信対象でも既読が少ない(年0.96件 vs 1.31件) | F6: ①と同じ順番(重視テーマ → 他の特性の基本) | G6: ='入力'!$G$21 | H6: ='④費用計算'!E7 | I6: ='④費用計算'!H7 | J6: 重視テーマを読み、理解度を上げる | K6: 既読医師率47%→54%(想定)、重視テーマの既読件数、理解度 | L6: 今の10本一律では、重視テーマ(内科=飲み合わせ、耳鼻=24h持続性)は配信の2割だけ。重視テーマを先頭にし、未読分を再配信して年10回→12回にする。
A7: ③ 意向ギャップ型 (内科12・耳鼻65) | B7: ='入力'!$B$22 | C7: ='入力'!$C$22 | D7: 処方意向は4以上(平均4.3)なのに処方率37% | E7: 処方意向は類似高処方医師(4.6)に近いが、処方率は37% vs 62%、理解度は3.0 vs 3.8 | F7: 処方場面の情報を中心に 内科: C09 多剤併用患者への処方設計、C04 併用時の注意点と実践 耳鼻: C10 長期投与の安全性と有効性、C05 臨床エビデンス、C02 適応症例集 | G7: ='入力'!$G$22 | H7: ='④費用計算'!E8 | I7: ='④費用計算'!H8 | J7: 処方意向を実際の処方につなげる | K7: 既読医師率55%→85%(想定)、処方率 | L7: 処方したい気持ちはすでにあり、既読も4タイプで最多(年1.09件)。処方場面の情報を年10回→24回(月2回)に増やす。
A8: ④ MR面談フォロー型 (内科41・耳鼻77、うち配信中82) | B8: 118 | C8: 1140 | D8: MR面談あり。理解度2.7・処方意向3.2・処方率31% | E8: 全員がMR面談あり(類似高処方医師は51%)。最も参考にした情報源の97%がMR対面 | F8: 変更なし(並び順だけ重視テーマを先頭に) | G8: ='入力'!$G$23 | H8: ='④費用計算'!E9 | I8: ='④費用計算'!H9 | J8: MR面談で対応(MR君は補完) | K8: 現状維持(MR面談での説明状況を確認) | L8: 主な情報源がMR対面のため、MR君の回数は変えない。
A9: (B案で追加) 未接触×潜在5〜7人 | B9: ='入力'!$B$24 | C9: ='入力'!$C$24 | D9: MR面談もMR君配信もない。理解度2.3・処方意向2.8。1人あたり潜在未処方5.9人 | E9: 重点医師(潜在8人以上)の次に伸びしろが大きい未接触層 | F9: ①と同じ順番 | G9: ='入力'!$H$24 | H9: ='④費用計算'!F10 | I9: ='④費用計算'!I10 | J9: MR君で初めて接点を持つ | K9: 既読医師率59%(想定)、理解度 | L9: 追加予算がある場合に、未接触の中で次に潜在が多い層へ月1回で広げる。
A10: (A案の財源) 配信中×潜在0〜2人 | B10: ='入力'!$B$25 | C10: ='入力'!$C$25 | D10: 1人あたり潜在未処方1.5人で伸びしろが小さい(処方率50%) | E10: — | F10: 重視テーマを中心に | G10: ='入力'!$G$25 | H10: ='④費用計算'!E11 | I10: ='④費用計算'!H11 | J10: 現在の処方を維持 | K10: 既読医師率51%→35%(想定)、処方率の維持 | L10: 年10回→6回(隔月)に減らし、浮いた既読予算を①〜③に回す。

Sheet ③配信計画
A1: ③ 配信計画(誰に・何回)
A4: 群 | B4: 現状回数 | C4: A案回数 | D4: B案回数 | E4: 配信医師数_現状 | F4: 配信医師数_A案 | G4: 配信医師数_B案 | H4: 配信件数_現状 | I4: 配信件数_A案 | J4: 配信件数_B案
A5: 接触不足型 | B5: ='入力'!$F$20 | C5: ='入力'!$G$20 | D5: ='入力'!$H$20 | E5: =IF('入力'!$F$20>0,'入力'!$B$20,0) | F5: =IF('入力'!$G$20>0,'入力'!$B$20,0) | G5: =IF('入力'!$H$20>0,'入力'!$B$20,0) | H5: ='入力'!$B$20*'入力'!$F$20 | I5: ='入力'!$B$20*'入力'!$G$20 | J5: ='入力'!$B$20*'入力'!$H$20
A6: 理解不足型 | B6: ='入力'!$F$21 | C6: ='入力'!$G$21 | D6: ='入力'!$H$21 | E6: =IF('入力'!$F$21>0,'入力'!$B$21,0) | F6: =IF('入力'!$G$21>0,'入力'!$B$21,0) | G6: =IF('入力'!$H$21>0,'入力'!$B$21,0) | H6: ='入力'!$B$21*'入力'!$F$21 | I6: ='入力'!$B$21*'入力'!$G$21 | J6: ='入力'!$B$21*'入力'!$H$21
A7: 意向ギャップ型 | B7: ='入力'!$F$22 | C7: ='入力'!$G$22 | D7: ='入力'!$H$22 | E7: =IF('入力'!$F$22>0,'入力'!$B$22,0) | F7: =IF('入力'!$G$22>0,'入力'!$B$22,0) | G7: =IF('入力'!$H$22>0,'入力'!$B$22,0) | H7: ='入力'!$B$22*'入力'!$F$22 | I7: ='入力'!$B$22*'入力'!$G$22 | J7: ='入力'!$B$22*'入力'!$H$22
A8: MR面談フォロー型(配信中) | B8: ='入力'!$F$23 | C8: ='入力'!$G$23 | D8: ='入力'!$H$23 | E8: =IF('入力'!$F$23>0,'入力'!$B$23,0) | F8: =IF('入力'!$G$23>0,'入力'!$B$23,0) | G8: =IF('入力'!$H$23>0,'入力'!$B$23,0) | H8: ='入力'!$B$23*'入力'!$F$23 | I8: ='入力'!$B$23*'入力'!$G$23 | J8: ='入力'!$B$23*'入力'!$H$23
A9: 未接触×潜在5〜7人 | B9: ='入力'!$F$24 | C9: ='入力'!$G$24 | D9: ='入力'!$H$24 | E9: =IF('入力'!$F$24>0,'入力'!$B$24,0) | F9: =IF('入力'!$G$24>0,'入力'!$B$24,0) | G9: =IF('入力'!$H$24>0,'入力'!$B$24,0) | H9: ='入力'!$B$24*'入力'!$F$24 | I9: ='入力'!$B$24*'入力'!$G$24 | J9: ='入力'!$B$24*'入力'!$H$24
A10: 低優先(配信中×潜在0〜2人) | B10: ='入力'!$F$25 | C10: ='入力'!$G$25 | D10: ='入力'!$H$25 | E10: =IF('入力'!$F$25>0,'入力'!$B$25,0) | F10: =IF('入力'!$G$25>0,'入力'!$B$25,0) | G10: =IF('入力'!$H$25>0,'入力'!$B$25,0) | H10: ='入力'!$B$25*'入力'!$F$25 | I10: ='入力'!$B$25*'入力'!$G$25 | J10: ='入力'!$B$25*'入力'!$H$25
A11: その他の配信中(変更なし) | B11: ='入力'!$F$26 | C11: ='入力'!$G$26 | D11: ='入力'!$H$26 | E11: =IF('入力'!$F$26>0,'入力'!$B$26,0) | F11: =IF('入力'!$G$26>0,'入力'!$B$26,0) | G11: =IF('入力'!$H$26>0,'入力'!$B$26,0) | H11: ='入力'!$B$26*'入力'!$F$26 | I11: ='入力'!$B$26*'入力'!$G$26 | J11: ='入力'!$B$26*'入力'!$H$26
A12: 合計 | E12: =SUM(E5:E11) | F12: =SUM(F5:F11) | G12: =SUM(G5:G11) | H12: =SUM(H5:H11) | I12: =SUM(I5:I11) | J12: =SUM(J5:J11)

Sheet ④費用計算
A1: ④ 費用計算: 既読件数 = 医師数 × 年間配信回数 × 1配信あたり既読率 / 費用 = 既読件数 × 既読単価
A2: 現状費用は回答医師分(全医師10,000名では既読8,192件・327.7万円)。配信設定・運用・制作費は未確認(①で入力)
A5: 群 | B5: 既読件数_現状 | C5: 費用_現状 | E5: 既読件数_A案 | F5: 既読件数_B案 | H5: 費用_A案 | I5: 費用_B案
A6: 接触不足型 | B6: ='入力'!$B$20*'入力'!$F$20*'入力'!$D$20 | C6: =B6*unit_price | E6: ='入力'!$B$20*'入力'!$G$20*'入力'!$D$20 | F6: ='入力'!$B$20*'入力'!$H$20*'入力'!$D$20 | H6: =E6*unit_price | I6: =F6*unit_price
A7: 理解不足型 | B7: ='入力'!$B$21*'入力'!$F$21*'入力'!$D$21 | C7: =B7*unit_price | E7: ='入力'!$B$21*'入力'!$G$21*'入力'!$D$21 | F7: ='入力'!$B$21*'入力'!$H$21*'入力'!$D$21 | H7: =E7*unit_price | I7: =F7*unit_price
A8: 意向ギャップ型 | B8: ='入力'!$B$22*'入力'!$F$22*'入力'!$D$22 | C8: =B8*unit_price | E8: ='入力'!$B$22*'入力'!$G$22*'入力'!$D$22 | F8: ='入力'!$B$22*'入力'!$H$22*'入力'!$D$22 | H8: =E8*unit_price | I8: =F8*unit_price
A9: MR面談フォロー型(配信中) | B9: ='入力'!$B$23*'入力'!$F$23*'入力'!$D$23 | C9: =B9*unit_price | E9: ='入力'!$B$23*'入力'!$G$23*'入力'!$D$23 | F9: ='入力'!$B$23*'入力'!$H$23*'入力'!$D$23 | H9: =E9*unit_price | I9: =F9*unit_price
A10: 未接触×潜在5〜7人 | B10: ='入力'!$B$24*'入力'!$F$24*'入力'!$D$24 | C10: =B10*unit_price | E10: ='入力'!$B$24*'入力'!$G$24*'入力'!$D$24 | F10: ='入力'!$B$24*'入力'!$H$24*'入力'!$D$24 | H10: =E10*unit_price | I10: =F10*unit_price
A11: 低優先(配信中×潜在0〜2人) | B11: ='入力'!$B$25*'入力'!$F$25*'入力'!$D$25 | C11: =B11*unit_price | E11: ='入力'!$B$25*'入力'!$G$25*'入力'!$D$25 | F11: ='入力'!$B$25*'入力'!$H$25*'入力'!$D$25 | H11: =E11*unit_price | I11: =F11*unit_price
A12: その他の配信中(変更なし) | B12: ='入力'!$B$26*'入力'!$F$26*'入力'!$D$26 | C12: =B12*unit_price | E12: ='入力'!$B$26*'入力'!$G$26*'入力'!$D$26 | F12: ='入力'!$B$26*'入力'!$H$26*'入力'!$D$26 | H12: =E12*unit_price | I12: =F12*unit_price
A13: 既読費用 合計 | B13: =SUM(B6:B12) | C13: =SUM(C6:C12) | E13: =SUM(E6:E12) | F13: =SUM(F6:F12) | H13: =SUM(H6:H12) | I13: =SUM(I6:I12)
A14: 制作費・運用費(未確認) | C14: 0 | H14: =prod_cost+ops_cost | I14: =prod_cost+ops_cost
A15: 総費用 | C15: =C13+C14 | H15: =H13+H14 | I15: =I13+I14
A16: 現状からの追加費用 | H16: =H15-C15 | I16: =I15-C15
A17: 予算判定(A案は現状費用以内か) | H17: =IF(H15<=C15,"予算内","予算超過")

Sheet ⑤売上試算
A1: ⑤ 売上試算: 既読医師率(f回) = 1 −(1 − 10回時の既読医師率)^(f/10) / 追加処方患者 = 既読医師の増加 × 1人あたり潜在未処方 × 増分転換率
A2: 施策をしなくても起きる変化は含めない(現状との差のみ)。各医師は1つの群にだけ属するため、効果の二重計上はない。売上であり利益ではない
H3: 追加処方患者(人)
A4: 群 | B4: 1人あたり潜在未処方 | C4: 既読医師率_現状 | D4: 既読医師率_A案 | E4: 既読医師率_B案 | F4: 既読医師の増加_A案 | G4: 既読医師の増加_B案 | H4: A案_保守 | I4: A案_基準 | J4: A案_楽観 | K4: B案_保守 | L4: B案_基準 | M4: B案_楽観
A5: 接触不足型 | B5: ='入力'!$C$20/'入力'!$B$20 | C5: =IF(OR('入力'!$E$20="",'入力'!$F$20=0),0,1-(1-'入力'!$E$20)^('入力'!$F$20/10)) | D5: =IF(OR('入力'!$E$20="",'入力'!$G$20=0),0,1-(1-'入力'!$E$20)^('入力'!$G$20/10)) | E5: =IF(OR('入力'!$E$20="",'入力'!$H$20=0),0,1-(1-'入力'!$E$20)^('入力'!$H$20/10)) | F5: =IF('入力'!$E$20="",0,'入力'!$B$20*(D5-C5)) | G5: =IF('入力'!$E$20="",0,'入力'!$B$20*(E5-C5)) | H5: =F5*B5*conv_low | I5: =F5*B5*conv_base | J5: =F5*B5*conv_high | K5: =G5*B5*conv_low | L5: =G5*B5*conv_base | M5: =G5*B5*conv_high
A6: 理解不足型 | B6: ='入力'!$C$21/'入力'!$B$21 | C6: =IF(OR('入力'!$E$21="",'入力'!$F$21=0),0,1-(1-'入力'!$E$21)^('入力'!$F$21/10)) | D6: =IF(OR('入力'!$E$21="",'入力'!$G$21=0),0,1-(1-'入力'!$E$21)^('入力'!$G$21/10)) | E6: =IF(OR('入力'!$E$21="",'入力'!$H$21=0),0,1-(1-'入力'!$E$21)^('入力'!$H$21/10)) | F6: =IF('入力'!$E$21="",0,'入力'!$B$21*(D6-C6)) | G6: =IF('入力'!$E$21="",0,'入力'!$B$21*(E6-C6)) | H6: =F6*B6*conv_low | I6: =F6*B6*conv_base | J6: =F6*B6*conv_high | K6: =G6*B6*conv_low | L6: =G6*B6*conv_base | M6: =G6*B6*conv_high
A7: 意向ギャップ型 | B7: ='入力'!$C$22/'入力'!$B$22 | C7: =IF(OR('入力'!$E$22="",'入力'!$F$22=0),0,1-(1-'入力'!$E$22)^('入力'!$F$22/10)) | D7: =IF(OR('入力'!$E$22="",'入力'!$G$22=0),0,1-(1-'入力'!$E$22)^('入力'!$G$22/10)) | E7: =IF(OR('入力'!$E$22="",'入力'!$H$22=0),0,1-(1-'入力'!$E$22)^('入力'!$H$22/10)) | F7: =IF('入力'!$E$22="",0,'入力'!$B$22*(D7-C7)) | G7: =IF('入力'!$E$22="",0,'入力'!$B$22*(E7-C7)) | H7: =F7*B7*conv_low | I7: =F7*B7*conv_base | J7: =F7*B7*conv_high | K7: =G7*B7*conv_low | L7: =G7*B7*conv_base | M7: =G7*B7*conv_high
A8: MR面談フォロー型(配信中) | B8: ='入力'!$C$23/'入力'!$B$23 | C8: =IF(OR('入力'!$E$23="",'入力'!$F$23=0),0,1-(1-'入力'!$E$23)^('入力'!$F$23/10)) | D8: =IF(OR('入力'!$E$23="",'入力'!$G$23=0),0,1-(1-'入力'!$E$23)^('入力'!$G$23/10)) | E8: =IF(OR('入力'!$E$23="",'入力'!$H$23=0),0,1-(1-'入力'!$E$23)^('入力'!$H$23/10)) | F8: =IF('入力'!$E$23="",0,'入力'!$B$23*(D8-C8)) | G8: =IF('入力'!$E$23="",0,'入力'!$B$23*(E8-C8)) | H8: =F8*B8*conv_low | I8: =F8*B8*conv_base | J8: =F8*B8*conv_high | K8: =G8*B8*conv_low | L8: =G8*B8*conv_base | M8: =G8*B8*conv_high
A9: 未接触×潜在5〜7人 | B9: ='入力'!$C$24/'入力'!$B$24 | C9: =IF(OR('入力'!$E$24="",'入力'!$F$24=0),0,1-(1-'入力'!$E$24)^('入力'!$F$24/10)) | D9: =IF(OR('入力'!$E$24="",'入力'!$G$24=0),0,1-(1-'入力'!$E$24)^('入力'!$G$24/10)) | E9: =IF(OR('入力'!$E$24="",'入力'!$H$24=0),0,1-(1-'入力'!$E$24)^('入力'!$H$24/10)) | F9: =IF('入力'!$E$24="",0,'入力'!$B$24*(D9-C9)) | G9: =IF('入力'!$E$24="",0,'入力'!$B$24*(E9-C9)) | H9: =F9*B9*conv_low | I9: =F9*B9*conv_base | J9: =F9*B9*conv_high | K9: =G9*B9*conv_low | L9: =G9*B9*conv_base | M9: =G9*B9*conv_high
A10: 低優先(配信中×潜在0〜2人) | B10: ='入力'!$C$25/'入力'!$B$25 | C10: =IF(OR('入力'!$E$25="",'入力'!$F$25=0),0,1-(1-'入力'!$E$25)^('入力'!$F$25/10)) | D10: =IF(OR('入力'!$E$25="",'入力'!$G$25=0),0,1-(1-'入力'!$E$25)^('入力'!$G$25/10)) | E10: =IF(OR('入力'!$E$25="",'入力'!$H$25=0),0,1-(1-'入力'!$E$25)^('入力'!$H$25/10)) | F10: =IF('入力'!$E$25="",0,'入力'!$B$25*(D10-C10)) | G10: =IF('入力'!$E$25="",0,'入力'!$B$25*(E10-C10)) | H10: =F10*B10*conv_low | I10: =F10*B10*conv_base | J10: =F10*B10*conv_high | K10: =G10*B10*conv_low | L10: =G10*B10*conv_base | M10: =G10*B10*conv_high
A11: その他の配信中(変更なし) | B11: ='入力'!$C$26/'入力'!$B$26 | C11: =IF(OR('入力'!$E$26="",'入力'!$F$26=0),0,1-(1-'入力'!$E$26)^('入力'!$F$26/10)) | D11: =IF(OR('入力'!$E$26="",'入力'!$G$26=0),0,1-(1-'入力'!$E$26)^('入力'!$G$26/10)) | E11: =IF(OR('入力'!$E$26="",'入力'!$H$26=0),0,1-(1-'入力'!$E$26)^('入力'!$H$26/10)) | F11: =IF('入力'!$E$26="",0,'入力'!$B$26*(D11-C11)) | G11: =IF('入力'!$E$26="",0,'入力'!$B$26*(E11-C11)) | H11: =F11*B11*conv_low | I11: =F11*B11*conv_base | J11: =F11*B11*conv_high | K11: =G11*B11*conv_low | L11: =G11*B11*conv_base | M11: =G11*B11*conv_high
A12: 追加処方患者 合計 | F12: =SUM(F5:F11) | G12: =SUM(G5:G11) | H12: =SUM(H5:H11) | I12: =SUM(I5:I11) | J12: =SUM(J5:J11) | K12: =SUM(K5:K11) | L12: =SUM(L5:L11) | M12: =SUM(M5:M11)
A13: 追加売上(円) = 追加処方患者 × 処方患者1人あたり年間売上 | H13: =H12*sales_per_pt | I13: =I12*sales_per_pt | J13: =J12*sales_per_pt | K13: =K12*sales_per_pt | L13: =L12*sales_per_pt | M13: =M12*sales_per_pt

Sheet ⑥シナリオ比較
A1: ⑥ シナリオ比較: A案(予算維持型)とB案(追加投資型)
A2: A案: 低優先(潜在0〜2人)の配信を年10回→6回に減らし、接触不足型を新規配信・理解不足型を年12回・意向ギャップ型を年24回に。B案: A案+未接触×潜在5〜7人260名を新規配信(年12回)
A4: 項目 | B4: 現状 | C4: A案 予算維持型 | D4: B案 追加投資型 | E4: B案 − A案
A5: 配信対象医師数(名) | B5: ='③配信計画'!E12 | C5: ='③配信計画'!F12 | D5: ='③配信計画'!G12 | E5: =D5-C5
A6: 配信件数(件) | B6: ='③配信計画'!H12 | C6: ='③配信計画'!I12 | D6: ='③配信計画'!J12 | E6: =D6-C6
A7: 想定既読件数(件) | B7: ='④費用計算'!B13 | C7: ='④費用計算'!E13 | D7: ='④費用計算'!F13 | E7: =D7-C7
A8: 費用(円) | B8: ='④費用計算'!C15 | C8: ='④費用計算'!H15 | D8: ='④費用計算'!I15 | E8: =D8-C8
A9: 現状からの追加費用(円) | B9: 0 | C9: =C8-$B$8 | D9: =D8-$B$8 | E9: =D9-C9
A10: 潜在患者カバー数(人) | B10: =SUMPRODUCT(('入力'!$F$20:$F$26>0)*'入力'!$C$20:$C$26) | C10: =SUMPRODUCT(('入力'!$G$20:$G$26>0)*'入力'!$C$20:$C$26) | D10: =SUMPRODUCT(('入力'!$H$20:$H$26>0)*'入力'!$C$20:$C$26) | E10: =D10-C10
A11: 追加処方患者_保守(人) | B11: 0 | C11: ='⑤売上試算'!H12 | D11: ='⑤売上試算'!K12 | E11: =D11-C11
A12: 追加処方患者_基準(人) | B12: 0 | C12: ='⑤売上試算'!I12 | D12: ='⑤売上試算'!L12 | E12: =D12-C12
A13: 追加処方患者_楽観(人) | B13: 0 | C13: ='⑤売上試算'!J12 | D13: ='⑤売上試算'!M12 | E13: =D13-C13
A14: 追加売上_保守(円) | B14: 0 | C14: ='⑤売上試算'!H13 | D14: ='⑤売上試算'!K13 | E14: =D14-C14
A15: 追加売上_基準(円) | B15: 0 | C15: ='⑤売上試算'!I13 | D15: ='⑤売上試算'!L13 | E15: =D15-C15
A16: 追加売上_楽観(円) | B16: 0 | C16: ='⑤売上試算'!J13 | D16: ='⑤売上試算'!M13 | E16: =D16-C16
A17: 費用対効果(追加売上_基準 ÷ 追加費用) | C17: =IF(C9<=0,"追加費用なし",C15/C9) | D17: =IF(D9<=0,"追加費用なし",D15/D9) | E17: =IF(E9<=0,"",E15/E9)
A18: 費用回収に必要な利益率_保守(追加費用÷追加売上) | C18: =IF(C9<=0,"不要",C9/C14) | D18: =IF(D9<=0,"不要",D9/D14) | E18: =IF(E9<=0,"",E9/E14)
A19: 費用回収に必要な利益率_基準 | C19: =IF(C9<=0,"不要",C9/C15) | D19: =IF(D9<=0,"不要",D9/D15) | E19: =IF(E9<=0,"",E9/E15)
A20: 予算判定(A案) | C20: =IF(C8<=B8,"予算内","予算超過")
A22: 表示用(PPTと同じ丸め) | B22: 現状 | C22: A案 | D22: B案 | E22: B案 − A案
A23: 費用(万円、小数1桁) | B23: =ROUND(B8/10000,1) | C23: =ROUND(C8/10000,1) | D23: =ROUND(D8/10000,1) | E23: =ROUND(D8/10000,1)-ROUND(C8/10000,1)
A24: 追加費用(万円、小数1桁) | B24: =ROUND(B9/10000,1) | C24: =ROUND(C9/10000,1) | D24: =ROUND(D9/10000,1) | E24: =ROUND(D9/10000,1)-ROUND(C9/10000,1)
A25: 既読件数 | B25: =ROUND(B7,0) | C25: =ROUND(C7,0) | D25: =ROUND(D7,0) | E25: =ROUND(D7,0)-ROUND(C7,0)
A26: 追加処方患者_保守 | B26: =ROUND(B11,0) | C26: =ROUND(C11,0) | D26: =ROUND(D11,0) | E26: =ROUND(E11,0)
A27: 追加処方患者_基準 | B27: =ROUND(B12,0) | C27: =ROUND(C12,0) | D27: =ROUND(D12,0) | E27: =ROUND(E12,0)
A28: 追加処方患者_楽観 | B28: =ROUND(B13,0) | C28: =ROUND(C13,0) | D28: =ROUND(D13,0) | E28: =ROUND(E13,0)
A29: 追加売上_保守(万円) | B29: =ROUND(B14/10000,0) | C29: =ROUND(C14/10000,0) | D29: =ROUND(D14/10000,0) | E29: =ROUND(D14/10000,0)-ROUND(C14/10000,0)
A30: 追加売上_基準(万円) | B30: =ROUND(B15/10000,0) | C30: =ROUND(C15/10000,0) | D30: =ROUND(D15/10000,0) | E30: =ROUND(D15/10000,0)-ROUND(C15/10000,0)
A31: 追加売上_楽観(万円) | B31: =ROUND(B16/10000,0) | C31: =ROUND(C16/10000,0) | D31: =ROUND(D16/10000,0) | E31: =ROUND(D16/10000,0)-ROUND(C16/10000,0)

Sheet ⑦計算根拠・注意事項
A1: ⑦ 計算根拠・注意事項
A3: 【実測】医師数・潜在未処方・既読件数・既読医師率は、2026年アンケート(回答5,000名)とMR君の配信対象・既読ログ(1年分)から集計(analysis/v4_analysis.py)。
A4: 【資料】既読単価400円、年間売上50億円、現状の配信は配信対象1名に10本(課題資料「10コンテンツを対象医師に配信」)。
A5: 【仮定】処方患者1人あたり年間売上 = 50億円 ÷ 全医師の処方患者推計22,560人(回答医師11,280人×10,000/5,000)。全医師10,000名の処方が売上のすべてと仮定。
A6: 【仮定】既読医師率のモデル: 年f回配信時 = 1 −(1 − 10回時の既読医師率)^(f/10)。配信ごとの既読のしやすさが一定と仮定。10回より多い配信は未読分の再配信を含む。
A7: 【仮定】増分転換率(保守1%・基準3%・楽観6%): 既読した医師の潜在未処方のうち、配信によって新たに処方される割合。
A8: 参考値(観察、因果ではない): MR面談のない両年回答2,945名で、配信対象は対象外より処方率の伸びが2.3pt大きかった(95%区間1.1〜3.5pt、診療科・2025年の処方率・理解度・意向で調整)。
A9: これを既読医師1人・潜在未処方あたりに換算すると約6.0%(下限2.8%)。楽観=中央、基準=下限、保守=その約3分の1。2025年時点の状態は両群でほぼ同じ(標準化差は最大0.06)だが、無作為ではない。
A10: 【予測区間の理由】①増分転換率(配信と処方の関係が観察データのみ) ②再配信時の既読率(未検証) ③1人あたり売上(単価・処方日数が不明) ④自己申告の患者数(年ごとに変動)。
A11: 【含めないもの】コンテンツの並べ替え・出し分けによる上乗せ効果(未検証のため0)、MR面談フォロー型の変化(現状維持)、施策をしなくても起きる処方の変化。
A12: 【売上と利益】追加売上は売上であり利益ではない。利益率が不明のため、費用との比較は「費用回収に必要な利益率」で示す。
A13: 【未確認の実施条件】新規配信先(接触不足型191名・未接触×潜在5〜7人260名)の配信資格・同意・配信停止、MR君で医師別に配信順・回数を指定できるか、制作費・運用費。
... A15: 【使わない分析】他グループの資料で扱われた完読・コンテンツ別の処方効果・動画の長さの分析は、本試算に使用していない。
